{
  "segments": [
    {
      "start": 0.0,
      "end": 4.0,
      "text": "morning yoga for stress relief को कुरा गर्दा धेरैले एउटा ठूलो कुरा छुटाउँछन्।"
    },
    {
      "start": 4.0,
      "end": 10.0,
      "text": "समस्या देखिन्छ, तर त्यसको जरा, असर र समाधानलाई एकैसाथ कमै बुझिन्छ।"
    },
    {
      "start": 10.0,
      "end": 20.0,
      "text": "morning yoga for stress relief ले रोजगारी, शिक्षा, अर्थतन्त्र र जनताको दैनिकीमा सीधा प्रभाव पार्छ। तथ्यसहित बुझ्दा मात्र राम्रो निर्णय सम्भव हुन्छ।"
    },
    {
      "start": 20.0,
      "end": 31.0,
      "text": "समाधान भनेको स्पष्ट योजना, जवाफदेही नेतृत्व, स्थानीय सहभागिता र कामको नतिजा मापन गर्नु हो। नेपालका धेरै समस्या सही सोच र निरन्तर कामले सुधारिन सक्छन्।"
    },
    {
      "start": 31.0,
      "end": 34.0,
      "text": "यस्ता तथ्यपूर्ण नेपाली Shorts का लागि follow Janapakchya Nepal"
    }
  ]
}